echofish_aws_raw_to_zarr_dlq_lambda/__init__.py
echofish_aws_raw_to_zarr_dlq_lambda/lambda_executor.py
echofish_aws_raw_to_zarr_dlq_lambda/lambda_handler.py
echofish_aws_raw_to_zarr_dlq_lambda-1.0.0.dev20230524162855.dist-info/LICENSE
echofish_aws_raw_to_zarr_dlq_lambda-1.0.0.dev20230524162855.dist-info/METADATA
echofish_aws_raw_to_zarr_dlq_lambda-1.0.0.dev20230524162855.dist-info/WHEEL
echofish_aws_raw_to_zarr_dlq_lambda-1.0.0.dev20230524162855.dist-info/top_level.txt
echofish_aws_raw_to_zarr_dlq_lambda-1.0.0.dev20230524162855.dist-info/RECORD
