Metadata-Version: 2.1
Name: echofish-aws-raw-to-zarr-dlq-lambda
Version: 1.0.0.dev20230524162855
Home-page: https://github.com/ci-cmg/echofish-aws-raw-to-zarr-dlq-lambda
Classifier: Programming Language :: Python :: 3.9
Classifier: License :: OSI Approved :: MIT License
Requires-Python: >=3.9
License-File: LICENSE
Requires-Dist: boto3 (==1.26.126)
Requires-Dist: botocore (==1.29.126)
